pesp/__doc__.py
pesp/__init__.py
pesp/__main__.py
pesp/crypto.py
pesp/dns.py
pesp/enums.py
pesp/ip.py
pesp/message.py
pesp/server.py
pvpn/__doc__.py
pvpn/__init__.py
pvpn/__main__.py
pvpn/crypto.py
pvpn/dns.py
pvpn/enums.py
pvpn/ip.py
pvpn/message.py
pvpn/server.py
pvpn-0.2.5.dist-info/LICENSE
pvpn-0.2.5.dist-info/METADATA
pvpn-0.2.5.dist-info/WHEEL
pvpn-0.2.5.dist-info/entry_points.txt
pvpn-0.2.5.dist-info/top_level.txt
pvpn-0.2.5.dist-info/RECORD
