Metadata-Version: 1.2
Name: pvpn
Version: 0.2.5
Summary: Python VPN server.
Home-page: https://github.com/qwj/python-vpn
Author: Qian Wenjie
Author-email: qianwenjie@gmail.com
License: MIT
Keywords: vpn ike esp ip tcp udp wireguard
Platform: UNKNOWN
Classifier: Development Status :: 5 - Production/Stable
Classifier: Environment :: Console
Classifier: Intended Audience :: Developers
Classifier: Natural Language :: English
Classifier: Topic :: Software Development :: Build Tools
Classifier: License :: OSI Approved :: MIT License
Classifier: Programming Language :: Python :: 3
Classifier: Programming Language :: Python :: 3.6
Classifier: Programming Language :: Python :: 3.7
Classifier: Programming Language :: Python :: 3.8
Classifier: Programming Language :: Python :: 3.9
Classifier: Programming Language :: Python :: 3.10
Requires-Python: >=3.6
